[
    {
      "title": "Squat Kickback",
      "time": "60 seconds",
      "thumbnail": "assets/thumbnail1.jpg",
      "videoUrl": "https://youtu.be/06DMc1EP-Sk"
    },
    {
      "title": "Squat with Side Leg Lift",
      "time": "120 seconds",
      "thumbnail": "assets/thumbnail2.jpg",
      "videoUrl": "https://youtu.be/06DMc1EP-Sk"
    },
    {
      "title": "Leg press",
      "time": "90 seconds",
      "thumbnail": "assets/thumbnail1.jpg",
      "videoUrl": "https://youtu.be/06DMc1EP-Sk"
    },
    {
      "title": "Leg extensions",
      "time": "60 seconds",
      "thumbnail": "assets/thumbnail2.jpg",
      "videoUrl": "https://youtu.be/06DMc1EP-Sk"
    },
    {
      "title": "Leg curl",
      "time": "90 seconds",
      "thumbnail": "assets/thumbnail1.jpg",
      "videoUrl": "https://youtu.be/06DMc1EP-Sk"
    },
    {
      "title": "Snatch",
      "time": "120 seconds",
      "thumbnail": "assets/thumbnail2.jpg",
      "videoUrl": "https://youtu.be/06DMc1EP-Sk"
    },
    {
      "title": "Deaflift",
      "time": "60 seconds",
      "thumbnail": "assets/thumbnail1.jpg",
      "videoUrl": "https://youtu.be/06DMc1EP-Sk"
    }
  ]